pump_analyzer/__init__.py
pump_analyzer/toolbox/__init__.py
pump_analyzer/toolbox/V1/Method_fault_analyzer.py
pump_analyzer/toolbox/V1/__init__.py
pump_analyzer/validation/__init__.py
pump_analyzer/validation/V1/__init__.py
pump_analyzer/validation/V1/validation_pump_model.py
fault_analyzer-0.3.0.dist-info/LICENSE
fault_analyzer-0.3.0.dist-info/METADATA
fault_analyzer-0.3.0.dist-info/WHEEL
fault_analyzer-0.3.0.dist-info/top_level.txt
fault_analyzer-0.3.0.dist-info/RECORD
