Metadata-Version: 2.1
Name: fault-analyzer
Version: 0.3.0
Summary: A Python library for Pump failure Analyzer
Home-page: https://github.com/MRHU2015114057/pump_model
Author: Hu Nan
Author-email: 709043890@qq.com
Classifier: License :: OSI Approved :: MIT License
Classifier: Programming Language :: Python :: 3
Classifier: Programming Language :: Python :: 3.6
Classifier: Programming Language :: Python :: 3.7
Classifier: Programming Language :: Python :: 3.8
License-File: LICENSE
